severstar_mfc_rs485/__init__.py
severstar_mfc_rs485/__main__.py
severstar_mfc_rs485/cli.py
severstar_mfc_rs485/commands.py
severstar_mfc_rs485/communication.py
severstar_mfc_rs485/exceptions.py
severstar_mfc_rs485/protocol.py
severstar_mfc_rs485/severstar_mfc_rs485.py
severstar_mfc_rs485/utils.py
severstar_mfc_rs485-0.1.0.dist-info/licenses/LICENSE
severstar_mfc_rs485-0.1.0.dist-info/METADATA
severstar_mfc_rs485-0.1.0.dist-info/WHEEL
severstar_mfc_rs485-0.1.0.dist-info/entry_points.txt
severstar_mfc_rs485-0.1.0.dist-info/top_level.txt
severstar_mfc_rs485-0.1.0.dist-info/RECORD
