Metadata-Version: 2.4
Name: severstar-mfc-rs485
Version: 0.1.0
Summary: Python code for RS485 communication with Severstar MFC
Author-email: Gavin Lou <gavinlou@kingsphase.page>
Maintainer-email: Gavin Lou <gavinlou@kingsphase.page>
License: MIT
Project-URL: bugs, https://github.com/gavinlouuu-kpt/severstar_mfc_rs485/issues
Project-URL: changelog, https://github.com/gavinlouuu-kpt/severstar_mfc_rs485/blob/master/changelog.md
Project-URL: homepage, https://github.com/gavinlouuu-kpt/severstar_mfc_rs485
Requires-Python: >=3.10
License-File: LICENSE
Requires-Dist: typer
Requires-Dist: pyserial
Provides-Extra: test
Requires-Dist: coverage; extra == "test"
Requires-Dist: pytest; extra == "test"
Requires-Dist: ruff; extra == "test"
Requires-Dist: ty; extra == "test"
Requires-Dist: ipdb; extra == "test"
Dynamic: license-file
